tableplus/__init__.py
tableplus/cli.py
tableplus/core.py
tableplus_db_urls-0.1.4.dist-info/AUTHORS.md
tableplus_db_urls-0.1.4.dist-info/LICENSE
tableplus_db_urls-0.1.4.dist-info/METADATA
tableplus_db_urls-0.1.4.dist-info/WHEEL
tableplus_db_urls-0.1.4.dist-info/entry_points.txt
tableplus_db_urls-0.1.4.dist-info/top_level.txt
tableplus_db_urls-0.1.4.dist-info/RECORD
