Metadata-Version: 2.1
Name: tableplus-db-urls
Version: 0.1.4
Summary: Generate TablePlus DB URLs from CookieCutter Django to make setting up connections easier.
Author-email: Tim Santor <tsantor@xstudios.com>
Project-URL: Repository, https://github.com/tsantor/tableplus-db-urls.git
Project-URL: Issues, https://github.com/tsantor/tableplus-db-urls/issues
Project-URL: Changelog, https://github.com/tsantor/tableplus-db-urls/blob/master/HISTORY.md
Classifier: Development Status :: 5 - Production/Stable
Classifier: Environment :: Console
Classifier: Intended Audience :: Developers
Classifier: Natural Language :: English
Classifier: Programming Language :: Python :: 3.8
Classifier: Programming Language :: Python :: 3.9
Classifier: Programming Language :: Python :: 3.10
Classifier: Programming Language :: Python :: 3.11
Classifier: Programming Language :: Python :: 3.12
Requires-Python: >=3.8
License-File: LICENSE
License-File: AUTHORS.md
Requires-Dist: click
Requires-Dist: python-dotenv
Provides-Extra: dev
